get_file_type/README.md
get_file_type/__init__.py
get_file_type/file.exe
get_file_type/libmagic.dll
get_file_type/magic.mgc
get_file_type/requirements.txt
get_file_type/thirdparty.json
get_file_type-0.10.dist-info/LICENSE.rst
get_file_type-0.10.dist-info/METADATA
get_file_type-0.10.dist-info/WHEEL
get_file_type-0.10.dist-info/top_level.txt
get_file_type-0.10.dist-info/RECORD
