Metadata-Version: 2.1
Name: get-file-type
Version: 0.10
Summary: Guesses the file type/mime/encoding of files. It uses the binaries from File and Libmagic.
Home-page: https://github.com/hansalemaos/get_file_type
Author: Johannes Fischer
Author-email: aulasparticularesdealemaosp@gmail.com
License: MIT
Keywords: file,types,mime
Classifier: Development Status :: 4 - Beta
Classifier: Programming Language :: Python :: 3 :: Only
Classifier: Programming Language :: Python :: 3.10
Classifier: Topic :: Software Development :: Libraries :: Python Modules
Classifier: Topic :: Utilities
License-File: LICENSE.rst
Requires-Dist: getfilenuitkapython
Requires-Dist: list-all-files-recursively
